Metadata-Version: 1.0
Name: turjuman
Version: 1.0.5
Summary: TURJUMAN, a neural toolkit for translating from 20 languages into Modern Standard Arabic (MSA).
Home-page: https://github.com/UBC-NLP/turjuman
Author: Moataz Nagoudi, AbdelRahim Elmadany, and Muhammad Abdul-Mageed
Author-email: a.elmadany@ubc.ca
License: GPL
Platform: UNKNOWN
